toolium/__init__.py
toolium/config_driver.py
toolium/config_driver_playwright.py
toolium/config_files.py
toolium/config_parser.py
toolium/driver_wrapper.py
toolium/driver_wrappers_pool.py
toolium/jira.py
toolium/pytest_fixtures.py
toolium/selenoid.py
toolium/test_cases.py
toolium/visual_test.py
toolium/behave/__init__.py
toolium/behave/env_utils.py
toolium/behave/environment.py
toolium/pageelements/__init__.py
toolium/pageelements/button_page_element.py
toolium/pageelements/checkbox_page_element.py
toolium/pageelements/group_page_element.py
toolium/pageelements/input_radio_page_element.py
toolium/pageelements/input_text_page_element.py
toolium/pageelements/link_page_element.py
toolium/pageelements/page_element.py
toolium/pageelements/page_elements.py
toolium/pageelements/select_page_element.py
toolium/pageelements/text_page_element.py
toolium/pageelements/playwright/__init__.py
toolium/pageelements/playwright/button_page_element.py
toolium/pageelements/playwright/input_text_page_element.py
toolium/pageelements/playwright/page_element.py
toolium/pageelements/playwright/text_page_element.py
toolium/pageobjects/__init__.py
toolium/pageobjects/common_object.py
toolium/pageobjects/mobile_page_object.py
toolium/pageobjects/page_object.py
toolium/resources/VisualTests.css
toolium/resources/VisualTests.js
toolium/resources/VisualTestsTemplate.html
toolium/utils/__init__.py
toolium/utils/data_generator.py
toolium/utils/dataset.py
toolium/utils/download_files.py
toolium/utils/driver_utils.py
toolium/utils/driver_wait_utils.py
toolium/utils/path_utils.py
toolium/utils/poeditor.py
toolium-3.5.0.dist-info/licenses/LICENSE
toolium-3.5.0.dist-info/METADATA
toolium-3.5.0.dist-info/WHEEL
toolium-3.5.0.dist-info/top_level.txt
toolium-3.5.0.dist-info/RECORD
