Metadata-Version: 2.4
Name: toolium
Version: 3.5.0
Summary: Wrapper tool of Selenium and Appium libraries to test web and mobile applications in a single project
Home-page: https://github.com/telefonica/toolium
Author: Rubén González Alonso, Telefónica I+D
Author-email: ruben.gonzalezalonso@telefonica.com
License: Apache 2.0
Keywords: selenium appium webdriver web_automation mobile_automation page_object visual_testing bdd behave pytest
Classifier: Development Status :: 5 - Production/Stable
Classifier: Intended Audience :: Developers
Classifier: Intended Audience :: Other Audience
Classifier: License :: OSI Approved :: Apache Software License
Classifier: Natural Language :: English
Classifier: Operating System :: OS Independent
Classifier: Programming Language :: Python :: 3.9
Classifier: Programming Language :: Python :: 3.10
Classifier: Programming Language :: Python :: 3.11
Classifier: Programming Language :: Python :: 3.12
Classifier: Programming Language :: Python :: 3.13
Classifier: Topic :: Software Development :: Libraries :: Python Modules
Classifier: Topic :: Software Development :: Quality Assurance
Classifier: Topic :: Software Development :: Testing
License-File: LICENSE
Requires-Dist: requests~=2.27
Requires-Dist: selenium~=4.0
Requires-Dist: Appium-Python-Client<5.0,>=2.3
Requires-Dist: Pillow~=10.1
Requires-Dist: screeninfo~=0.8
Requires-Dist: lxml~=5.1
Requires-Dist: Faker~=25.9
Requires-Dist: phonenumbers~=8.13
Provides-Extra: playwright
Requires-Dist: playwright~=1.43; extra == "playwright"
Dynamic: author
Dynamic: author-email
Dynamic: classifier
Dynamic: description
Dynamic: description-content-type
Dynamic: home-page
Dynamic: keywords
Dynamic: license
Dynamic: license-file
Dynamic: provides-extra
Dynamic: requires-dist
Dynamic: summary
